pyeditorconfig/__init__.py
pyeditorconfig/pyeditorconfig.py
pyeditorconfig-1.0.0.dist-info/LICENSE
pyeditorconfig-1.0.0.dist-info/METADATA
pyeditorconfig-1.0.0.dist-info/WHEEL
pyeditorconfig-1.0.0.dist-info/top_level.txt
pyeditorconfig-1.0.0.dist-info/RECORD
