Metadata-Version: 2.1
Name: pyeditorconfig
Version: 1.0.0
Summary: A better way to handle .editorconfig files with Python.
Home-page: https://github.com/Moosems/pyeditorconfig
Author: Moosems
Author-email: moosems.j@gmail.com
License: MIT license
Requires-Python: >=3.7
License-File: LICENSE
